werkflow_python/__init__.py
werkflow_python/python.py
werkflow_python-0.1.1.dist-info/licenses/LICENSE
werkflow_python-0.1.1.dist-info/METADATA
werkflow_python-0.1.1.dist-info/WHEEL
werkflow_python-0.1.1.dist-info/top_level.txt
werkflow_python-0.1.1.dist-info/RECORD
